pytest_mypy_plugins/__init__.py
pytest_mypy_plugins/collect.py
pytest_mypy_plugins/configs.py
pytest_mypy_plugins/item.py
pytest_mypy_plugins/py.typed
pytest_mypy_plugins/schema.json
pytest_mypy_plugins/utils.py
pytest_mypy_plugins-3.2.0.dist-info/LICENSE
pytest_mypy_plugins-3.2.0.dist-info/METADATA
pytest_mypy_plugins-3.2.0.dist-info/WHEEL
pytest_mypy_plugins-3.2.0.dist-info/entry_points.txt
pytest_mypy_plugins-3.2.0.dist-info/top_level.txt
pytest_mypy_plugins-3.2.0.dist-info/RECORD
