Metadata-Version: 2.1
Name: pytest-mypy-plugins
Version: 3.2.0
Summary: pytest plugin for writing tests for mypy plugins
Home-page: https://github.com/TypedDjango/pytest-mypy-plugins
Author: Maksim Kurnikov
Author-email: maxim.kurnikov@gmail.com
Maintainer: Nikita Sobolev
Maintainer-email: mail@sobolevn.me
License: MIT
Classifier: Development Status :: 4 - Beta
Classifier: License :: OSI Approved :: MIT License
Classifier: Programming Language :: Python :: 3
Classifier: Programming Language :: Python :: 3.9
Classifier: Programming Language :: Python :: 3.10
Classifier: Programming Language :: Python :: 3.11
Classifier: Programming Language :: Python :: 3.12
Classifier: Programming Language :: Python :: 3.13
Classifier: Typing :: Typed
Requires-Python: >=3.9
License-File: LICENSE
Requires-Dist: Jinja2
Requires-Dist: decorator
Requires-Dist: jsonschema
Requires-Dist: mypy>=1.3
Requires-Dist: packaging
Requires-Dist: pytest>=7.0.0
Requires-Dist: pyyaml
Requires-Dist: regex
Requires-Dist: tomlkit>=0.11
